shuup_graphql/__init__.py
shuup_graphql/apps.py
shuup_graphql/settings.py
shuup_graphql/urls.py
shuup_graphql/views.py
shuup_graphql/admin/__init__.py
shuup_graphql/admin/mutations/__init__.py
shuup_graphql/admin/queries/__init__.py
shuup_graphql/admin/queries/_users.py
shuup_graphql/front/__init__.py
shuup_graphql/front/mutations/__init__.py
shuup_graphql/front/mutations/_basket.py
shuup_graphql/front/mutations/_category.py
shuup_graphql/front/mutations/_product.py
shuup_graphql/front/queries/__init__.py
shuup_graphql/front/queries/_basket.py
shuup_graphql/front/queries/_category.py
shuup_graphql/front/queries/_manufacturer.py
shuup_graphql/front/queries/_product.py
shuup_graphql/front/queries/_product_media.py
shuup_graphql/front/queries/_shop_product.py
shuup_graphql/front/queries/_supplier.py
shuup_graphql/front/queries/_user.py
shuup_graphql/front/types/__init__.py
shuup_graphql/front/types/address.py
shuup_graphql/front/types/basket.py
shuup_graphql/front/types/category.py
shuup_graphql/front/types/contact.py
shuup_graphql/front/types/filer.py
shuup_graphql/front/types/manufacturer.py
shuup_graphql/front/types/price.py
shuup_graphql/front/types/product.py
shuup_graphql/front/types/product_media.py
shuup_graphql/front/types/sales_unit.py
shuup_graphql/front/types/shop.py
shuup_graphql/front/types/shop_product.py
shuup_graphql/front/types/supplier.py
shuup_graphql/front/types/user.py
shuup_graphql/front/utils/__init__.py
shuup_graphql/front/utils/filer.py
shuup_graphql/front/utils/shop_product.py
shuup_graphql_tests/__init__.py
shuup_graphql_tests/settings.py
shuup_graphql_tests/urls.py
shuup_graphql_tests/admin/__init__.py
shuup_graphql_tests/admin/test_queries.py
shuup_graphql_tests/front/__init__.py
shuup_graphql_tests/front/test_basket.py
shuup_graphql_tests/front/test_category.py
shuup_graphql_tests/front/test_manufacturer.py
shuup_graphql_tests/front/test_shop_products.py
shuup_graphql_tests/front/test_user.py
shuup_graphql-0.1.2.dist-info/LICENSE
shuup_graphql-0.1.2.dist-info/METADATA
shuup_graphql-0.1.2.dist-info/WHEEL
shuup_graphql-0.1.2.dist-info/top_level.txt
shuup_graphql-0.1.2.dist-info/RECORD
